Workbook

Sheet Leeme
A1: Punto de equilibrio y sensibilidad de precios (datos ficticios)
A2: Servicio de ejemplo: estudio de imagen en un centro de salud. Todas las cifras son inventadas.
A4: Hojas:
A5: Supuestos: datos de entrada (celdas azules con fondo amarillo; son las únicas que se editan).
A6: Equilibrio: margen de contribución, punto de equilibrio, margen de seguridad y gráfico ingresos vs. costos.
A7: Sensibilidad: utilidad según el precio (-20 % a +30 %) con elasticidad constante, y precio óptimo.
A8: Elasticidad: tabla de dos entradas, utilidad según precio y elasticidad.
A10: Código de colores: azul = dato de entrada; negro = fórmula. Verde = resultado clave.
A11: Modelo de demanda: Q = Q0 × (P / P0)^(-e). Supuesto simplificado; no incluye capacidad ni competencia.

Sheet Supuestos
A1: Supuesto | B1: Valor | C1: Nota
A2: Precio actual (USD) | B2: 120 | C2: Precio por estudio
A3: Costo variable unitario (USD) | B3: 45 | C3: Insumos, honorarios por estudio
A4: Costos fijos mensuales (USD) | B4: 38000 | C4: Equipo, personal fijo, arriendo
A5: Volumen actual (estudios/mes) | B5: 800 | C5: Línea base
A6: Elasticidad precio de la demanda (e) | B6: 1.5 | C6: Supuesto del analista; ver hoja Elasticidad para 0,5–2,5
A7: Paso de variación de precio | B7: 0.05 | C7: Incremento entre escenarios
A9: Ejemplo de formato: precio 120,00; costo variable 45,00; volumen 800. Datos ficticios, sin relación con ningún empleador.

Sheet Equilibrio
A1: Indicador | B1: Valor
A2: Margen de contribución unitario (USD) | B2: =Supuestos!B2-Supuestos!B3 -> 75
A3: Margen de contribución (%) | B3: =B2/Supuestos!B2 -> 0.625
A4: Punto de equilibrio (estudios/mes) | B4: =Supuestos!B4/B2 -> 506.66667
A5: Punto de equilibrio (ingresos USD/mes) | B5: =B4*Supuestos!B2 -> 60800
A6: Ingresos actuales (USD/mes) | B6: =Supuestos!B5*Supuestos!B2 -> 96000
A7: Utilidad operativa actual (USD/mes) | B7: =Supuestos!B5*B2-Supuestos!B4 -> 22000
A8: Margen de seguridad (%) | B8: =(Supuestos!B5-B4)/Supuestos!B5 -> 0.36666667
A9: Estudios adicionales para ganar USD 10.000 más | B9: =10000/B2 -> 133.33333 | C9: 10.000 es un objetivo ilustrativo (supuesto).
A12: Volumen (estudios/mes) | B12: Ingresos | C12: Costos totales | D12: Utilidad
A13: =0 -> 0 | B13: =A13*Supuestos!$B$2 -> 0 | C13: =Supuestos!$B$4+A13*Supuestos!$B$3 -> 38000 | D13: =B13-C13 -> -38000
A14: =A13+200 -> 200 | B14: =A14*Supuestos!$B$2 -> 24000 | C14: =Supuestos!$B$4+A14*Supuestos!$B$3 -> 47000 | D14: =B14-C14 -> -23000
A15: =A14+200 -> 400 | B15: =A15*Supuestos!$B$2 -> 48000 | C15: =Supuestos!$B$4+A15*Supuestos!$B$3 -> 56000 | D15: =B15-C15 -> -8000
A16: =A15+200 -> 600 | B16: =A16*Supuestos!$B$2 -> 72000 | C16: =Supuestos!$B$4+A16*Supuestos!$B$3 -> 65000 | D16: =B16-C16 -> 7000
A17: =A16+200 -> 800 | B17: =A17*Supuestos!$B$2 -> 96000 | C17: =Supuestos!$B$4+A17*Supuestos!$B$3 -> 74000 | D17: =B17-C17 -> 22000
A18: =A17+200 -> 1000 | B18: =A18*Supuestos!$B$2 -> 120000 | C18: =Supuestos!$B$4+A18*Supuestos!$B$3 -> 83000 | D18: =B18-C18 -> 37000
A19: =A18+200 -> 1200 | B19: =A19*Supuestos!$B$2 -> 144000 | C19: =Supuestos!$B$4+A19*Supuestos!$B$3 -> 92000 | D19: =B19-C19 -> 52000
A20: =A19+200 -> 1400 | B20: =A20*Supuestos!$B$2 -> 168000 | C20: =Supuestos!$B$4+A20*Supuestos!$B$3 -> 101000 | D20: =B20-C20 -> 67000
A21: =A20+200 -> 1600 | B21: =A21*Supuestos!$B$2 -> 192000 | C21: =Supuestos!$B$4+A21*Supuestos!$B$3 -> 110000 | D21: =B21-C21 -> 82000
A22: =A21+200 -> 1800 | B22: =A22*Supuestos!$B$2 -> 216000 | C22: =Supuestos!$B$4+A22*Supuestos!$B$3 -> 119000 | D22: =B22-C22 -> 97000
A23: =A22+200 -> 2000 | B23: =A23*Supuestos!$B$2 -> 240000 | C23: =Supuestos!$B$4+A23*Supuestos!$B$3 -> 128000 | D23: =B23-C23 -> 112000

Sheet Sensibilidad
A1: Variación de precio | B1: Precio (USD) | C1: Volumen estimado | D1: Ingresos | E1: Costos variables | F1: Margen de contribución | G1: Utilidad operativa | H1: Punto de equilibrio (estudios) | I1: Margen de seguridad
A2: =-0.2 -> -0.2 | B2: =Supuestos!$B$2*(1+A2) -> 96 | C2: =Supuestos!$B$5*(B2/Supuestos!$B$2)^(-Supuestos!$B$6) -> 1118.034 | D2: =B2*C2 -> 107331.26 | E2: =C2*Supuestos!$B$3 -> 50311.529 | F2: =D2-E2 -> 57019.733 | G2: =F2-Supuestos!$B$4 -> 19019.733 | H2: =IF(B2>Supuestos!$B$3,Supuestos!$B$4/(B2-Supuestos!$B$3),"n/a") -> 745.09804 | I2: =IFERROR((C2-H2)/C2,"n/a") -> 0.33356405
A3: =A2+Supuestos!$B$7 -> -0.15 | B3: =Supuestos!$B$2*(1+A3) -> 102 | C3: =Supuestos!$B$5*(B3/Supuestos!$B$2)^(-Supuestos!$B$6) -> 1020.8492 | D3: =B3*C3 -> 104126.62 | E3: =C3*Supuestos!$B$3 -> 45938.215 | F3: =D3-E3 -> 58188.405 | G3: =F3-Supuestos!$B$4 -> 20188.405 | H3: =IF(B3>Supuestos!$B$3,Supuestos!$B$4/(B3-Supuestos!$B$3),"n/a") -> 666.66667 | I3: =IFERROR((C3-H3)/C3,"n/a") -> 0.34694893
A4: =A3+Supuestos!$B$7 -> -0.1 | B4: =Supuestos!$B$2*(1+A4) -> 108 | C4: =Supuestos!$B$5*(B4/Supuestos!$B$2)^(-Supuestos!$B$6) -> 936.97116 | D4: =B4*C4 -> 101192.89 | E4: =C4*Supuestos!$B$3 -> 42163.702 | F4: =D4-E4 -> 59029.183 | G4: =F4-Supuestos!$B$4 -> 21029.183 | H4: =IF(B4>Supuestos!$B$3,Supuestos!$B$4/(B4-Supuestos!$B$3),"n/a") -> 603.1746 | I4: =IFERROR((C4-H4)/C4,"n/a") -> 0.35625062
A5: =A4+Supuestos!$B$7 -> -0.05 | B5: =Supuestos!$B$2*(1+A5) -> 114 | C5: =Supuestos!$B$5*(B5/Supuestos!$B$2)^(-Supuestos!$B$6) -> 863.98177 | D5: =B5*C5 -> 98493.922 | E5: =C5*Supuestos!$B$3 -> 38879.18 | F5: =D5-E5 -> 59614.742 | G5: =F5-Supuestos!$B$4 -> 21614.742 | H5: =IF(B5>Supuestos!$B$3,Supuestos!$B$4/(B5-Supuestos!$B$3),"n/a") -> 550.72464 | I5: =IFERROR((C5-H5)/C5,"n/a") -> 0.36257378
A6: =A5+Supuestos!$B$7 -> 0 | B6: =Supuestos!$B$2*(1+A6) -> 120 | C6: =Supuestos!$B$5*(B6/Supuestos!$B$2)^(-Supuestos!$B$6) -> 800 | D6: =B6*C6 -> 96000 | E6: =C6*Supuestos!$B$3 -> 36000 | F6: =D6-E6 -> 60000 | G6: =F6-Supuestos!$B$4 -> 22000 | H6: =IF(B6>Supuestos!$B$3,Supuestos!$B$4/(B6-Supuestos!$B$3),"n/a") -> 506.66667 | I6: =IFERROR((C6-H6)/C6,"n/a") -> 0.36666667
A7: =A6+Supuestos!$B$7 -> 0.05 | B7: =Supuestos!$B$2*(1+A7) -> 126 | C7: =Supuestos!$B$5*(B7/Supuestos!$B$2)^(-Supuestos!$B$6) -> 743.54291 | D7: =B7*C7 -> 93686.407 | E7: =C7*Supuestos!$B$3 -> 33459.431 | F7: =D7-E7 -> 60226.976 | G7: =F7-Supuestos!$B$4 -> 22226.976 | H7: =IF(B7>Supuestos!$B$3,Supuestos!$B$4/(B7-Supuestos!$B$3),"n/a") -> 469.1358 | I7: =IFERROR((C7-H7)/C7,"n/a") -> 0.36905349
A8: =A7+Supuestos!$B$7 -> 0.1 | B8: =Supuestos!$B$2*(1+A8) -> 132 | C8: =Supuestos!$B$5*(B8/Supuestos!$B$2)^(-Supuestos!$B$6) -> 693.42734 | D8: =B8*C8 -> 91532.409 | E8: =C8*Supuestos!$B$3 -> 31204.23 | F8: =D8-E8 -> 60328.178 | G8: =F8-Supuestos!$B$4 -> 22328.178 | H8: =IF(B8>Supuestos!$B$3,Supuestos!$B$4/(B8-Supuestos!$B$3),"n/a") -> 436.78161 | I8: =IFERROR((C8-H8)/C8,"n/a") -> 0.37011193
A9: =A8+Supuestos!$B$7 -> 0.15 | B9: =Supuestos!$B$2*(1+A9) -> 138 | C9: =Supuestos!$B$5*(B9/Supuestos!$B$2)^(-Supuestos!$B$6) -> 648.699 | D9: =B9*C9 -> 89520.462 | E9: =C9*Supuestos!$B$3 -> 29191.455 | F9: =D9-E9 -> 60329.007 | G9: =F9-Supuestos!$B$4 -> 22329.007 | H9: =IF(B9>Supuestos!$B$3,Supuestos!$B$4/(B9-Supuestos!$B$3),"n/a") -> 408.60215 | I9: =IFERROR((C9-H9)/C9,"n/a") -> 0.37012058
A10: =A9+Supuestos!$B$7 -> 0.2 | B10: =Supuestos!$B$2*(1+A10) -> 144 | C10: =Supuestos!$B$5*(B10/Supuestos!$B$2)^(-Supuestos!$B$6) -> 608.58062 | D10: =B10*C10 -> 87635.609 | E10: =C10*Supuestos!$B$3 -> 27386.128 | F10: =D10-E10 -> 60249.481 | G10: =F10-Supuestos!$B$4 -> 22249.481 | H10: =IF(B10>Supuestos!$B$3,Supuestos!$B$4/(B10-Supuestos!$B$3),"n/a") -> 383.83838 | I10: =IFERROR((C10-H10)/C10,"n/a") -> 0.36928918
A11: =A10+Supuestos!$B$7 -> 0.25 | B11: =Supuestos!$B$2*(1+A11) -> 150 | C11: =Supuestos!$B$5*(B11/Supuestos!$B$2)^(-Supuestos!$B$6) -> 572.4334 | D11: =B11*C11 -> 85865.01 | E11: =C11*Supuestos!$B$3 -> 25759.503 | F11: =D11-E11 -> 60105.507 | G11: =F11-Supuestos!$B$4 -> 22105.507 | H11: =IF(B11>Supuestos!$B$3,Supuestos!$B$4/(B11-Supuestos!$B$3),"n/a") -> 361.90476 | I11: =IFERROR((C11-H11)/C11,"n/a") -> 0.3677784
A12: =A11+Supuestos!$B$7 -> 0.3 | B12: =Supuestos!$B$2*(1+A12) -> 156 | C12: =Supuestos!$B$5*(B12/Supuestos!$B$2)^(-Supuestos!$B$6) -> 539.72801 | D12: =B12*C12 -> 84197.57 | E12: =C12*Supuestos!$B$3 -> 24287.761 | F12: =D12-E12 -> 59909.809 | G12: =F12-Supuestos!$B$4 -> 21909.809 | H12: =IF(B12>Supuestos!$B$3,Supuestos!$B$4/(B12-Supuestos!$B$3),"n/a") -> 342.34234 | I12: =IFERROR((C12-H12)/C12,"n/a") -> 0.36571322
A15: Precio de mayor utilidad (en la grilla) | B15: =INDEX(B2:B12,MATCH(MAX(G2:G12),G2:G12,0)) -> 138
A16: Utilidad en ese precio (USD/mes) | B16: =MAX(G2:G12) -> 22329.007
A17: Mejora vs. utilidad actual (USD/mes) | B17: =B16-Equilibrio!B7 -> 329.00672
A18: Precio óptimo teórico = e/(e-1) × costo variable | B18: =IF(Supuestos!B6>1,Supuestos!B6/(Supuestos!B6-1)*Supuestos!B3,"n/a (e ≤ 1)") -> 135
A19: El precio óptimo teórico es válido sin restricciones de capacidad ni competencia; la grilla lo contrasta con escenarios discretos.

Sheet Elasticidad
A1: Utilidad operativa mensual (USD) según variación de precio (filas) y elasticidad (columnas)
A2: Variación \ e | B2: 0.5 | C2: 1 | D2: 1.5 | E2: 2 | F2: 2.5
A3: =Sensibilidad!A2 -> -0.2 | B3: =Supuestos!$B$5*(1+$A3)^(-B$2)*Supuestos!$B$2*(1+$A3)-Supuestos!$B$5*(1+$A3)^(-B$2)*Supuestos!$B$3-Supuestos!$B$4 -> 7615.7867 | C3: =Supuestos!$B$5*(1+$A3)^(-C$2)*Supuestos!$B$2*(1+$A3)-Supuestos!$B$5*(1+$A3)^(-C$2)*Supuestos!$B$3-Supuestos!$B$4 -> 13000 | D3: =Supuestos!$B$5*(1+$A3)^(-D$2)*Supuestos!$B$2*(1+$A3)-Supuestos!$B$5*(1+$A3)^(-D$2)*Supuestos!$B$3-Supuestos!$B$4 -> 19019.733 | E3: =Supuestos!$B$5*(1+$A3)^(-E$2)*Supuestos!$B$2*(1+$A3)-Supuestos!$B$5*(1+$A3)^(-E$2)*Supuestos!$B$3-Supuestos!$B$4 -> 25750 | F3: =Supuestos!$B$5*(1+$A3)^(-F$2)*Supuestos!$B$2*(1+$A3)-Supuestos!$B$5*(1+$A3)^(-F$2)*Supuestos!$B$3-Supuestos!$B$4 -> 33274.667
A4: =Sensibilidad!A3 -> -0.15 | B4: =Supuestos!$B$5*(1+$A4)^(-B$2)*Supuestos!$B$2*(1+$A4)-Supuestos!$B$5*(1+$A4)^(-B$2)*Supuestos!$B$3-Supuestos!$B$4 -> 11460.144 | C4: =Supuestos!$B$5*(1+$A4)^(-C$2)*Supuestos!$B$2*(1+$A4)-Supuestos!$B$5*(1+$A4)^(-C$2)*Supuestos!$B$3-Supuestos!$B$4 -> 15647.059 | D4: =Supuestos!$B$5*(1+$A4)^(-D$2)*Supuestos!$B$2*(1+$A4)-Supuestos!$B$5*(1+$A4)^(-D$2)*Supuestos!$B$3-Supuestos!$B$4 -> 20188.405 | E4: =Supuestos!$B$5*(1+$A4)^(-E$2)*Supuestos!$B$2*(1+$A4)-Supuestos!$B$5*(1+$A4)^(-E$2)*Supuestos!$B$3-Supuestos!$B$4 -> 25114.187 | F4: =Supuestos!$B$5*(1+$A4)^(-F$2)*Supuestos!$B$2*(1+$A4)-Supuestos!$B$5*(1+$A4)^(-F$2)*Supuestos!$B$3-Supuestos!$B$4 -> 30456.947
A5: =Sensibilidad!A4 -> -0.1 | B5: =Supuestos!$B$5*(1+$A5)^(-B$2)*Supuestos!$B$2*(1+$A5)-Supuestos!$B$5*(1+$A5)^(-B$2)*Supuestos!$B$3-Supuestos!$B$4 -> 15126.265 | C5: =Supuestos!$B$5*(1+$A5)^(-C$2)*Supuestos!$B$2*(1+$A5)-Supuestos!$B$5*(1+$A5)^(-C$2)*Supuestos!$B$3-Supuestos!$B$4 -> 18000 | D5: =Supuestos!$B$5*(1+$A5)^(-D$2)*Supuestos!$B$2*(1+$A5)-Supuestos!$B$5*(1+$A5)^(-D$2)*Supuestos!$B$3-Supuestos!$B$4 -> 21029.183 | E5: =Supuestos!$B$5*(1+$A5)^(-E$2)*Supuestos!$B$2*(1+$A5)-Supuestos!$B$5*(1+$A5)^(-E$2)*Supuestos!$B$3-Supuestos!$B$4 -> 24222.222 | F5: =Supuestos!$B$5*(1+$A5)^(-F$2)*Supuestos!$B$2*(1+$A5)-Supuestos!$B$5*(1+$A5)^(-F$2)*Supuestos!$B$3-Supuestos!$B$4 -> 27587.981
A6: =Sensibilidad!A5 -> -0.05 | B6: =Supuestos!$B$5*(1+$A6)^(-B$2)*Supuestos!$B$2*(1+$A6)-Supuestos!$B$5*(1+$A6)^(-B$2)*Supuestos!$B$3-Supuestos!$B$4 -> 18634.005 | C6: =Supuestos!$B$5*(1+$A6)^(-C$2)*Supuestos!$B$2*(1+$A6)-Supuestos!$B$5*(1+$A6)^(-C$2)*Supuestos!$B$3-Supuestos!$B$4 -> 20105.263 | D6: =Supuestos!$B$5*(1+$A6)^(-D$2)*Supuestos!$B$2*(1+$A6)-Supuestos!$B$5*(1+$A6)^(-D$2)*Supuestos!$B$3-Supuestos!$B$4 -> 21614.742 | E6: =Supuestos!$B$5*(1+$A6)^(-E$2)*Supuestos!$B$2*(1+$A6)-Supuestos!$B$5*(1+$A6)^(-E$2)*Supuestos!$B$3-Supuestos!$B$4 -> 23163.435 | F6: =Supuestos!$B$5*(1+$A6)^(-F$2)*Supuestos!$B$2*(1+$A6)-Supuestos!$B$5*(1+$A6)^(-F$2)*Supuestos!$B$3-Supuestos!$B$4 -> 24752.36
A7: =Sensibilidad!A6 -> 0 | B7: =Supuestos!$B$5*(1+$A7)^(-B$2)*Supuestos!$B$2*(1+$A7)-Supuestos!$B$5*(1+$A7)^(-B$2)*Supuestos!$B$3-Supuestos!$B$4 -> 22000 | C7: =Supuestos!$B$5*(1+$A7)^(-C$2)*Supuestos!$B$2*(1+$A7)-Supuestos!$B$5*(1+$A7)^(-C$2)*Supuestos!$B$3-Supuestos!$B$4 -> 22000 | D7: =Supuestos!$B$5*(1+$A7)^(-D$2)*Supuestos!$B$2*(1+$A7)-Supuestos!$B$5*(1+$A7)^(-D$2)*Supuestos!$B$3-Supuestos!$B$4 -> 22000 | E7: =Supuestos!$B$5*(1+$A7)^(-E$2)*Supuestos!$B$2*(1+$A7)-Supuestos!$B$5*(1+$A7)^(-E$2)*Supuestos!$B$3-Supuestos!$B$4 -> 22000 | F7: =Supuestos!$B$5*(1+$A7)^(-F$2)*Supuestos!$B$2*(1+$A7)-Supuestos!$B$5*(1+$A7)^(-F$2)*Supuestos!$B$3-Supuestos!$B$4 -> 22000
A8: =Sensibilidad!A7 -> 0.05 | B8: =Supuestos!$B$5*(1+$A8)^(-B$2)*Supuestos!$B$2*(1+$A8)-Supuestos!$B$5*(1+$A8)^(-B$2)*Supuestos!$B$3-Supuestos!$B$4 -> 25238.325 | C8: =Supuestos!$B$5*(1+$A8)^(-C$2)*Supuestos!$B$2*(1+$A8)-Supuestos!$B$5*(1+$A8)^(-C$2)*Supuestos!$B$3-Supuestos!$B$4 -> 23714.286 | D8: =Supuestos!$B$5*(1+$A8)^(-D$2)*Supuestos!$B$2*(1+$A8)-Supuestos!$B$5*(1+$A8)^(-D$2)*Supuestos!$B$3-Supuestos!$B$4 -> 22226.976 | E8: =Supuestos!$B$5*(1+$A8)^(-E$2)*Supuestos!$B$2*(1+$A8)-Supuestos!$B$5*(1+$A8)^(-E$2)*Supuestos!$B$3-Supuestos!$B$4 -> 20775.51 | F8: =Supuestos!$B$5*(1+$A8)^(-F$2)*Supuestos!$B$2*(1+$A8)-Supuestos!$B$5*(1+$A8)^(-F$2)*Supuestos!$B$3-Supuestos!$B$4 -> 19359.025
A9: =Sensibilidad!A8 -> 0.1 | B9: =Supuestos!$B$5*(1+$A9)^(-B$2)*Supuestos!$B$2*(1+$A9)-Supuestos!$B$5*(1+$A9)^(-B$2)*Supuestos!$B$3-Supuestos!$B$4 -> 28360.996 | C9: =Supuestos!$B$5*(1+$A9)^(-C$2)*Supuestos!$B$2*(1+$A9)-Supuestos!$B$5*(1+$A9)^(-C$2)*Supuestos!$B$3-Supuestos!$B$4 -> 25272.727 | D9: =Supuestos!$B$5*(1+$A9)^(-D$2)*Supuestos!$B$2*(1+$A9)-Supuestos!$B$5*(1+$A9)^(-D$2)*Supuestos!$B$3-Supuestos!$B$4 -> 22328.178 | E9: =Supuestos!$B$5*(1+$A9)^(-E$2)*Supuestos!$B$2*(1+$A9)-Supuestos!$B$5*(1+$A9)^(-E$2)*Supuestos!$B$3-Supuestos!$B$4 -> 19520.661 | F9: =Supuestos!$B$5*(1+$A9)^(-F$2)*Supuestos!$B$2*(1+$A9)-Supuestos!$B$5*(1+$A9)^(-F$2)*Supuestos!$B$3-Supuestos!$B$4 -> 16843.799
A10: =Sensibilidad!A9 -> 0.15 | B10: =Supuestos!$B$5*(1+$A10)^(-B$2)*Supuestos!$B$2*(1+$A10)-Supuestos!$B$5*(1+$A10)^(-B$2)*Supuestos!$B$3-Supuestos!$B$4 -> 31378.358 | C10: =Supuestos!$B$5*(1+$A10)^(-C$2)*Supuestos!$B$2*(1+$A10)-Supuestos!$B$5*(1+$A10)^(-C$2)*Supuestos!$B$3-Supuestos!$B$4 -> 26695.652 | D10: =Supuestos!$B$5*(1+$A10)^(-D$2)*Supuestos!$B$2*(1+$A10)-Supuestos!$B$5*(1+$A10)^(-D$2)*Supuestos!$B$3-Supuestos!$B$4 -> 22329.007 | E10: =Supuestos!$B$5*(1+$A10)^(-E$2)*Supuestos!$B$2*(1+$A10)-Supuestos!$B$5*(1+$A10)^(-E$2)*Supuestos!$B$3-Supuestos!$B$4 -> 18257.089 | F10: =Supuestos!$B$5*(1+$A10)^(-F$2)*Supuestos!$B$2*(1+$A10)-Supuestos!$B$5*(1+$A10)^(-F$2)*Supuestos!$B$3-Supuestos!$B$4 -> 14460.006
A11: =Sensibilidad!A10 -> 0.2 | B11: =Supuestos!$B$5*(1+$A11)^(-B$2)*Supuestos!$B$2*(1+$A11)-Supuestos!$B$5*(1+$A11)^(-B$2)*Supuestos!$B$3-Supuestos!$B$4 -> 34299.378 | C11: =Supuestos!$B$5*(1+$A11)^(-C$2)*Supuestos!$B$2*(1+$A11)-Supuestos!$B$5*(1+$A11)^(-C$2)*Supuestos!$B$3-Supuestos!$B$4 -> 28000 | D11: =Supuestos!$B$5*(1+$A11)^(-D$2)*Supuestos!$B$2*(1+$A11)-Supuestos!$B$5*(1+$A11)^(-D$2)*Supuestos!$B$3-Supuestos!$B$4 -> 22249.481 | E11: =Supuestos!$B$5*(1+$A11)^(-E$2)*Supuestos!$B$2*(1+$A11)-Supuestos!$B$5*(1+$A11)^(-E$2)*Supuestos!$B$3-Supuestos!$B$4 -> 17000 | F11: =Supuestos!$B$5*(1+$A11)^(-F$2)*Supuestos!$B$2*(1+$A11)-Supuestos!$B$5*(1+$A11)^(-F$2)*Supuestos!$B$3-Supuestos!$B$4 -> 12207.901
A12: =Sensibilidad!A11 -> 0.25 | B12: =Supuestos!$B$5*(1+$A12)^(-B$2)*Supuestos!$B$2*(1+$A12)-Supuestos!$B$5*(1+$A12)^(-B$2)*Supuestos!$B$3-Supuestos!$B$4 -> 37131.884 | C12: =Supuestos!$B$5*(1+$A12)^(-C$2)*Supuestos!$B$2*(1+$A12)-Supuestos!$B$5*(1+$A12)^(-C$2)*Supuestos!$B$3-Supuestos!$B$4 -> 29200 | D12: =Supuestos!$B$5*(1+$A12)^(-D$2)*Supuestos!$B$2*(1+$A12)-Supuestos!$B$5*(1+$A12)^(-D$2)*Supuestos!$B$3-Supuestos!$B$4 -> 22105.507 | E12: =Supuestos!$B$5*(1+$A12)^(-E$2)*Supuestos!$B$2*(1+$A12)-Supuestos!$B$5*(1+$A12)^(-E$2)*Supuestos!$B$3-Supuestos!$B$4 -> 15760 | F12: =Supuestos!$B$5*(1+$A12)^(-F$2)*Supuestos!$B$2*(1+$A12)-Supuestos!$B$5*(1+$A12)^(-F$2)*Supuestos!$B$3-Supuestos!$B$4 -> 10084.406
A13: =Sensibilidad!A12 -> 0.3 | B13: =Supuestos!$B$5*(1+$A13)^(-B$2)*Supuestos!$B$2*(1+$A13)-Supuestos!$B$5*(1+$A13)^(-B$2)*Supuestos!$B$3-Supuestos!$B$4 -> 39882.752 | C13: =Supuestos!$B$5*(1+$A13)^(-C$2)*Supuestos!$B$2*(1+$A13)-Supuestos!$B$5*(1+$A13)^(-C$2)*Supuestos!$B$3-Supuestos!$B$4 -> 30307.692 | D13: =Supuestos!$B$5*(1+$A13)^(-D$2)*Supuestos!$B$2*(1+$A13)-Supuestos!$B$5*(1+$A13)^(-D$2)*Supuestos!$B$3-Supuestos!$B$4 -> 21909.809 | E13: =Supuestos!$B$5*(1+$A13)^(-E$2)*Supuestos!$B$2*(1+$A13)-Supuestos!$B$5*(1+$A13)^(-E$2)*Supuestos!$B$3-Supuestos!$B$4 -> 14544.379 | F13: =Supuestos!$B$5*(1+$A13)^(-F$2)*Supuestos!$B$2*(1+$A13)-Supuestos!$B$5*(1+$A13)^(-F$2)*Supuestos!$B$3-Supuestos!$B$4 -> 8084.4687
A15: Lectura: con e bajo conviene subir el precio; con e alto, el volumen perdido supera el margen ganado.
