Workbook

Sheet Leeme
A1: Presupuesto vs. real y flujo de caja a 12 meses (datos ficticios)
A2: Caso de ejemplo: unidad de servicios de un centro de salud. Todas las cifras son inventadas; el año es ilustrativo.
A4: Hojas:
A5: Supuestos: caja inicial, caja mínima, cobranza y tabla de escenarios (celdas azules con fondo amarillo = editables).
A6: Datos: tabla plana mes a mes con presupuesto y real (Ene–Jun real). Lista para conectarse a Power BI.
A7: Presupuesto_vs_Real: variación de ingresos separada en efecto volumen y efecto precio, y variación de utilidad.
A8: Flujo_Base / Flujo_Optimista / Flujo_Pesimista: 6 meses reales + 6 proyectados, cobros, pagos, caja final y alerta.
A9: Resumen: comparación de escenarios contra el presupuesto anual y gráfico de caja.
A11: Código de colores: azul = dato de entrada; negro = fórmula; verde = resultado clave.
A12: Proyección: los meses Jul–Dic parten del promedio de los últimos 3 meses reales (Abr–Jun) y aplican los parámetros del escenario.

Sheet Resumen
A1: Resumen por escenario (USD)
A3: Indicador | B3: Presupuesto | C3: Base | D3: Optimista | E3: Pesimista
A4: Ingresos del año | B4: =SUMPRODUCT(Datos!B2:B13,Datos!C2:C13) -> 1080000 | C4: =Flujo_Base!E17 -> 1054166.6 | D4: =Flujo_Optimista!E17 -> 1099776.3 | E4: =Flujo_Pesimista!E17 -> 1008073.5
A5: Utilidad operativa del año | B5: =B4-SUMPRODUCT(Datos!B2:B13,Datos!D2:D13)-SUM(Datos!E2:G13) -> 108000 | C5: =Flujo_Base!I17 -> 48334.12 | D5: =Flujo_Optimista!I17 -> 86513.946 | E5: =Flujo_Pesimista!I17 -> 9135.7698
A6: Utilidad vs. presupuesto | C6: =C5-$B$5 -> -59665.88 | D6: =D5-$B$5 -> -21486.054 | E6: =E5-$B$5 -> -98864.23
A7: Caja final en diciembre | C7: =Flujo_Base!M16 -> 107815.94 | D7: =Flujo_Optimista!M16 -> 151694.66 | E7: =Flujo_Pesimista!M16 -> 61492.144
A8: Caja mínima del año | C8: =MIN(Flujo_Base!M5:M16) -> 65786 | D8: =MIN(Flujo_Optimista!M5:M16) -> 65786 | E8: =MIN(Flujo_Pesimista!M5:M16) -> 61492.144
A9: Meses en alerta (caja < mínima) | C9: =COUNTIF(Flujo_Base!N5:N16,"ALERTA") -> 0 | D9: =COUNTIF(Flujo_Optimista!N5:N16,"ALERTA") -> 0 | E9: =COUNTIF(Flujo_Pesimista!N5:N16,"ALERTA") -> 2
A11: Presupuesto = 12 meses de la hoja Datos. Escenarios = 6 meses reales + 6 proyectados.

Sheet Supuestos
A1: Supuesto | B1: Valor | C1: Nota
A2: Caja inicial (USD) | B2: 60000 | C2: Saldo al 1 de enero
A3: Cuentas por cobrar iniciales (USD) | B3: 36000 | C3: Se cobran en enero
A4: Caja mínima (USD) | B4: 65000 | C4: Bajo este nivel se activa la alerta
A5: % de cobro en el mismo mes (meses reales) | B5: 0.6 | C5: El resto se cobra el mes siguiente
A8: Escenarios (meses Jul–Dic) | B8: Base | C8: Optimista | D8: Pesimista
A9: Crecimiento mensual del volumen | B9: 0.01 | C9: 0.025 | D9: -0.01
A10: Variación del precio | B10: 0 | C10: 0.03 | D10: -0.02
A11: Variación del costo variable unitario | B11: 0 | C11: -0.02 | D11: 0.04
A12: % de cobro en el mismo mes | B12: 0.6 | C12: 0.7 | D12: 0.45
A14: Todos los valores son supuestos del analista (ficticios). Ejemplo de formato: crecimiento 1,0 % = 0.01.

Sheet Datos
A1: Mes | B1: Volumen ppto | C1: Precio ppto | D1: Costo var. unit. ppto | E1: Personal ppto | F1: Arriendo ppto | G1: Otros fijos ppto | H1: Volumen real | I1: Precio real | J1: Costo var. unit. real | K1: Personal real | L1: Arriendo real | M1: Otros fijos real
A2: Ene | B2: 900 | C2: 100 | D2: 40 | E2: 30000 | F2: 8000 | G2: 7000 | H2: 870 | I2: 98 | J2: 41 | K2: 30500 | L2: 8000 | M2: 7200
A3: Feb | B3: 900 | C3: 100 | D3: 40 | E3: 30000 | F3: 8000 | G3: 7000 | H3: 905 | I3: 101 | J3: 40 | K3: 30500 | L3: 8000 | M3: 6800
A4: Mar | B4: 900 | C4: 100 | D4: 40 | E4: 30000 | F4: 8000 | G4: 7000 | H4: 860 | I4: 99 | J4: 42 | K4: 31000 | L4: 8000 | M4: 8100
A5: Abr | B5: 900 | C5: 100 | D5: 40 | E5: 30000 | F5: 8000 | G5: 7000 | H5: 880 | I5: 97 | J5: 43 | K5: 31000 | L5: 8000 | M5: 7400
A6: May | B6: 900 | C6: 100 | D6: 40 | E6: 30000 | F6: 8000 | G6: 7000 | H6: 845 | I6: 100 | J6: 41 | K6: 31200 | L6: 8000 | M6: 7000
A7: Jun | B7: 900 | C7: 100 | D7: 40 | E7: 30000 | F7: 8000 | G7: 7000 | H7: 890 | I7: 99 | J7: 42 | K7: 31200 | L7: 8000 | M7: 9000
A8: Jul | B8: 900 | C8: 100 | D8: 40 | E8: 30000 | F8: 8000 | G8: 7000
A9: Ago | B9: 900 | C9: 100 | D9: 40 | E9: 30000 | F9: 8000 | G9: 7000
A10: Sep | B10: 900 | C10: 100 | D10: 40 | E10: 30000 | F10: 8000 | G10: 7000
A11: Oct | B11: 900 | C11: 100 | D11: 40 | E11: 30000 | F11: 8000 | G11: 7000
A12: Nov | B12: 900 | C12: 100 | D12: 40 | E12: 30000 | F12: 8000 | G12: 7000
A13: Dic | B13: 900 | C13: 100 | D13: 40 | E13: 30000 | F13: 8000 | G13: 7000
A15: Jul–Dic sin real: se proyectan en las hojas Flujo_*. Datos ficticios.

Sheet Presupuesto_vs_Real
A1: Presupuesto vs. real, enero–junio (USD)
A2: Efecto volumen = (Vol. real − Vol. ppto) × Precio ppto. Efecto precio = (Precio real − Precio ppto) × Vol. real. Suman la variación de ingresos.
A4: Mes | B4: Ingresos ppto | C4: Ingresos real | D4: Var. ingresos | E4: Efecto volumen | F4: Efecto precio | G4: Costo variable ppto | H4: Costo variable real | I4: Gastos fijos ppto | J4: Gastos fijos real | K4: Utilidad ppto | L4: Utilidad real | M4: Var. utilidad | N4: Var. utilidad % | O4: Chequeo
A5: =Datos!A2 -> Ene | B5: =Datos!B2*Datos!C2 -> 90000 | C5: =Datos!H2*Datos!I2 -> 85260 | D5: =C5-B5 -> -4740 | E5: =(Datos!H2-Datos!B2)*Datos!C2 -> -3000 | F5: =(Datos!I2-Datos!C2)*Datos!H2 -> -1740 | G5: =Datos!B2*Datos!D2 -> 36000 | H5: =Datos!H2*Datos!J2 -> 35670 | I5: =Datos!E2+Datos!F2+Datos!G2 -> 45000 | J5: =Datos!K2+Datos!L2+Datos!M2 -> 45700 | K5: =B5-G5-I5 -> 9000 | L5: =C5-H5-J5 -> 3890 | M5: =L5-K5 -> -5110 | N5: =IF(K5=0,0,M5/K5) -> -0.56777778 | O5: =IF(ABS(D5-E5-F5)<0.01,"OK","REVISAR") -> OK
A6: =Datos!A3 -> Feb | B6: =Datos!B3*Datos!C3 -> 90000 | C6: =Datos!H3*Datos!I3 -> 91405 | D6: =C6-B6 -> 1405 | E6: =(Datos!H3-Datos!B3)*Datos!C3 -> 500 | F6: =(Datos!I3-Datos!C3)*Datos!H3 -> 905 | G6: =Datos!B3*Datos!D3 -> 36000 | H6: =Datos!H3*Datos!J3 -> 36200 | I6: =Datos!E3+Datos!F3+Datos!G3 -> 45000 | J6: =Datos!K3+Datos!L3+Datos!M3 -> 45300 | K6: =B6-G6-I6 -> 9000 | L6: =C6-H6-J6 -> 9905 | M6: =L6-K6 -> 905 | N6: =IF(K6=0,0,M6/K6) -> 0.10055556 | O6: =IF(ABS(D6-E6-F6)<0.01,"OK","REVISAR") -> OK
A7: =Datos!A4 -> Mar | B7: =Datos!B4*Datos!C4 -> 90000 | C7: =Datos!H4*Datos!I4 -> 85140 | D7: =C7-B7 -> -4860 | E7: =(Datos!H4-Datos!B4)*Datos!C4 -> -4000 | F7: =(Datos!I4-Datos!C4)*Datos!H4 -> -860 | G7: =Datos!B4*Datos!D4 -> 36000 | H7: =Datos!H4*Datos!J4 -> 36120 | I7: =Datos!E4+Datos!F4+Datos!G4 -> 45000 | J7: =Datos!K4+Datos!L4+Datos!M4 -> 47100 | K7: =B7-G7-I7 -> 9000 | L7: =C7-H7-J7 -> 1920 | M7: =L7-K7 -> -7080 | N7: =IF(K7=0,0,M7/K7) -> -0.78666667 | O7: =IF(ABS(D7-E7-F7)<0.01,"OK","REVISAR") -> OK
A8: =Datos!A5 -> Abr | B8: =Datos!B5*Datos!C5 -> 90000 | C8: =Datos!H5*Datos!I5 -> 85360 | D8: =C8-B8 -> -4640 | E8: =(Datos!H5-Datos!B5)*Datos!C5 -> -2000 | F8: =(Datos!I5-Datos!C5)*Datos!H5 -> -2640 | G8: =Datos!B5*Datos!D5 -> 36000 | H8: =Datos!H5*Datos!J5 -> 37840 | I8: =Datos!E5+Datos!F5+Datos!G5 -> 45000 | J8: =Datos!K5+Datos!L5+Datos!M5 -> 46400 | K8: =B8-G8-I8 -> 9000 | L8: =C8-H8-J8 -> 1120 | M8: =L8-K8 -> -7880 | N8: =IF(K8=0,0,M8/K8) -> -0.87555556 | O8: =IF(ABS(D8-E8-F8)<0.01,"OK","REVISAR") -> OK
A9: =Datos!A6 -> May | B9: =Datos!B6*Datos!C6 -> 90000 | C9: =Datos!H6*Datos!I6 -> 84500 | D9: =C9-B9 -> -5500 | E9: =(Datos!H6-Datos!B6)*Datos!C6 -> -5500 | F9: =(Datos!I6-Datos!C6)*Datos!H6 -> 0 | G9: =Datos!B6*Datos!D6 -> 36000 | H9: =Datos!H6*Datos!J6 -> 34645 | I9: =Datos!E6+Datos!F6+Datos!G6 -> 45000 | J9: =Datos!K6+Datos!L6+Datos!M6 -> 46200 | K9: =B9-G9-I9 -> 9000 | L9: =C9-H9-J9 -> 3655 | M9: =L9-K9 -> -5345 | N9: =IF(K9=0,0,M9/K9) -> -0.59388889 | O9: =IF(ABS(D9-E9-F9)<0.01,"OK","REVISAR") -> OK
A10: =Datos!A7 -> Jun | B10: =Datos!B7*Datos!C7 -> 90000 | C10: =Datos!H7*Datos!I7 -> 88110 | D10: =C10-B10 -> -1890 | E10: =(Datos!H7-Datos!B7)*Datos!C7 -> -1000 | F10: =(Datos!I7-Datos!C7)*Datos!H7 -> -890 | G10: =Datos!B7*Datos!D7 -> 36000 | H10: =Datos!H7*Datos!J7 -> 37380 | I10: =Datos!E7+Datos!F7+Datos!G7 -> 45000 | J10: =Datos!K7+Datos!L7+Datos!M7 -> 48200 | K10: =B10-G10-I10 -> 9000 | L10: =C10-H10-J10 -> 2530 | M10: =L10-K10 -> -6470 | N10: =IF(K10=0,0,M10/K10) -> -0.71888889 | O10: =IF(ABS(D10-E10-F10)<0.01,"OK","REVISAR") -> OK
A11: Total | B11: =SUM(B5:B10) -> 540000 | C11: =SUM(C5:C10) -> 519775 | D11: =SUM(D5:D10) -> -20225 | E11: =SUM(E5:E10) -> -15000 | F11: =SUM(F5:F10) -> -5225 | G11: =SUM(G5:G10) -> 216000 | H11: =SUM(H5:H10) -> 217855 | I11: =SUM(I5:I10) -> 270000 | ... M11: =SUM(M5:M10) -> -30980 | N11: =IF(K11=0,0,M11/K11) -> -0.5737037 | O11: =IF(COUNTIF(O5:O10,"OK")=6,"OK","REVISAR") -> OK

Sheet Flujo_Base
A1: Flujo de caja a 12 meses (USD)
A2: Escenario (1-3) | B2: 1 | C2: =INDEX(Supuestos!$B$8:$D$8,$B$2) -> Base | D2: Crec. vol. mensual | E2: =INDEX(Supuestos!$B$9:$D$9,$B$2) -> 0.01 | F2: Var. precio | G2: =INDEX(Supuestos!$B$10:$D$10,$B$2) -> 0 | H2: Var. costo var. | I2: =INDEX(Supuestos!$B$11:$D$11,$B$2) -> 0 | J2: % cobro mes | K2: =INDEX(Supuestos!$B$12:$D$12,$B$2) -> 0.6
A4: Mes | B4: Tipo | C4: Volumen | D4: Precio | E4: Ingresos | F4: Costo var. unit. | G4: Costo variable | H4: Gastos fijos | I4: Utilidad operativa | J4: Cobros | K4: Pagos | L4: Flujo neto | M4: Caja final | N4: Estado | O4: % cobro mes
A5: =Datos!A2 -> Ene | B5: Real | C5: =Datos!H2 -> 870 | D5: =Datos!I2 -> 98 | E5: =C5*D5 -> 85260 | F5: =Datos!J2 -> 41 | G5: =C5*F5 -> 35670 | H5: =Datos!K2+Datos!L2+Datos!M2 -> 45700 | I5: =E5-G5-H5 -> 3890 | J5: =E5*O5+Supuestos!$B$3 -> 87156 | K5: =G5+H5 -> 81370 | L5: =J5-K5 -> 5786 | M5: =Supuestos!$B$2+L5 -> 65786 | N5: =IF(M5<Supuestos!$B$4,"ALERTA","OK") -> OK | O5: =Supuestos!$B$5 -> 0.6
A6: =Datos!A3 -> Feb | B6: Real | C6: =Datos!H3 -> 905 | D6: =Datos!I3 -> 101 | E6: =C6*D6 -> 91405 | F6: =Datos!J3 -> 40 | G6: =C6*F6 -> 36200 | H6: =Datos!K3+Datos!L3+Datos!M3 -> 45300 | I6: =E6-G6-H6 -> 9905 | J6: =E6*O6+E5*(1-O5) -> 88947 | K6: =G6+H6 -> 81500 | L6: =J6-K6 -> 7447 | M6: =M5+L6 -> 73233 | N6: =IF(M6<Supuestos!$B$4,"ALERTA","OK") -> OK | O6: =Supuestos!$B$5 -> 0.6
A7: =Datos!A4 -> Mar | B7: Real | C7: =Datos!H4 -> 860 | D7: =Datos!I4 -> 99 | E7: =C7*D7 -> 85140 | F7: =Datos!J4 -> 42 | G7: =C7*F7 -> 36120 | H7: =Datos!K4+Datos!L4+Datos!M4 -> 47100 | I7: =E7-G7-H7 -> 1920 | J7: =E7*O7+E6*(1-O6) -> 87646 | K7: =G7+H7 -> 83220 | L7: =J7-K7 -> 4426 | M7: =M6+L7 -> 77659 | N7: =IF(M7<Supuestos!$B$4,"ALERTA","OK") -> OK | O7: =Supuestos!$B$5 -> 0.6
A8: =Datos!A5 -> Abr | B8: Real | C8: =Datos!H5 -> 880 | D8: =Datos!I5 -> 97 | E8: =C8*D8 -> 85360 | F8: =Datos!J5 -> 43 | G8: =C8*F8 -> 37840 | H8: =Datos!K5+Datos!L5+Datos!M5 -> 46400 | I8: =E8-G8-H8 -> 1120 | J8: =E8*O8+E7*(1-O7) -> 85272 | K8: =G8+H8 -> 84240 | L8: =J8-K8 -> 1032 | M8: =M7+L8 -> 78691 | N8: =IF(M8<Supuestos!$B$4,"ALERTA","OK") -> OK | O8: =Supuestos!$B$5 -> 0.6
A9: =Datos!A6 -> May | B9: Real | C9: =Datos!H6 -> 845 | D9: =Datos!I6 -> 100 | E9: =C9*D9 -> 84500 | F9: =Datos!J6 -> 41 | G9: =C9*F9 -> 34645 | H9: =Datos!K6+Datos!L6+Datos!M6 -> 46200 | I9: =E9-G9-H9 -> 3655 | J9: =E9*O9+E8*(1-O8) -> 84844 | K9: =G9+H9 -> 80845 | L9: =J9-K9 -> 3999 | M9: =M8+L9 -> 82690 | N9: =IF(M9<Supuestos!$B$4,"ALERTA","OK") -> OK | O9: =Supuestos!$B$5 -> 0.6
A10: =Datos!A7 -> Jun | B10: Real | C10: =Datos!H7 -> 890 | D10: =Datos!I7 -> 99 | E10: =C10*D10 -> 88110 | F10: =Datos!J7 -> 42 | G10: =C10*F10 -> 37380 | H10: =Datos!K7+Datos!L7+Datos!M7 -> 48200 | I10: =E10-G10-H10 -> 2530 | J10: =E10*O10+E9*(1-O9) -> 86666 | K10: =G10+H10 -> 85580 | L10: =J10-K10 -> 1086 | M10: =M9+L10 -> 83776 | N10: =IF(M10<Supuestos!$B$4,"ALERTA","OK") -> OK | O10: =Supuestos!$B$5 -> 0.6
A11: =Datos!A8 -> Jul | B11: Proyectado | C11: =AVERAGE($C$8:$C$10)*(1+$E$2)^1 -> 880.38333 | D11: =AVERAGE($D$8:$D$10)*(1+$G$2) -> 98.666667 | E11: =C11*D11 -> 86864.489 | F11: =AVERAGE($F$8:$F$10)*(1+$I$2) -> 42 | G11: =C11*F11 -> 36976.1 | H11: =AVERAGE($H$8:$H$10) -> 46933.333 | I11: =E11-G11-H11 -> 2955.0556 | J11: =E11*O11+E10*(1-O10) -> 87362.693 | K11: =G11+H11 -> 83909.433 | L11: =J11-K11 -> 3453.26 | M11: =M10+L11 -> 87229.26 | N11: =IF(M11<Supuestos!$B$4,"ALERTA","OK") -> OK | O11: =$K$2 -> 0.6
A12: =Datos!A9 -> Ago | B12: Proyectado | C12: =AVERAGE($C$8:$C$10)*(1+$E$2)^2 -> 889.18717 | D12: =AVERAGE($D$8:$D$10)*(1+$G$2) -> 98.666667 | E12: =C12*D12 -> 87733.134 | F12: =AVERAGE($F$8:$F$10)*(1+$I$2) -> 42 | G12: =C12*F12 -> 37345.861 | H12: =AVERAGE($H$8:$H$10) -> 46933.333 | I12: =E12-G12-H12 -> 3453.9394 | J12: =E12*O12+E11*(1-O11) -> 87385.676 | K12: =G12+H12 -> 84279.194 | L12: =J12-K12 -> 3106.4815 | M12: =M11+L12 -> 90335.741 | N12: =IF(M12<Supuestos!$B$4,"ALERTA","OK") -> OK | O12: =$K$2 -> 0.6
A13: =Datos!A10 -> Sep | B13: Proyectado | C13: =AVERAGE($C$8:$C$10)*(1+$E$2)^3 -> 898.07904 | D13: =AVERAGE($D$8:$D$10)*(1+$G$2) -> 98.666667 | E13: =C13*D13 -> 88610.465 | F13: =AVERAGE($F$8:$F$10)*(1+$I$2) -> 42 | G13: =C13*F13 -> 37719.32 | H13: =AVERAGE($H$8:$H$10) -> 46933.333 | I13: =E13-G13-H13 -> 3957.8122 | J13: =E13*O13+E12*(1-O12) -> 88259.533 | K13: =G13+H13 -> 84652.653 | L13: =J13-K13 -> 3606.8796 | M13: =M12+L13 -> 93942.621 | N13: =IF(M13<Supuestos!$B$4,"ALERTA","OK") -> OK | O13: =$K$2 -> 0.6
A14: =Datos!A11 -> Oct | B14: Proyectado | C14: =AVERAGE($C$8:$C$10)*(1+$E$2)^4 -> 907.05983 | D14: =AVERAGE($D$8:$D$10)*(1+$G$2) -> 98.666667 | E14: =C14*D14 -> 89496.57 | F14: =AVERAGE($F$8:$F$10)*(1+$I$2) -> 42 | G14: =C14*F14 -> 38096.513 | H14: =AVERAGE($H$8:$H$10) -> 46933.333 | I14: =E14-G14-H14 -> 4466.7236 | J14: =E14*O14+E13*(1-O13) -> 89142.128 | K14: =G14+H14 -> 85029.846 | L14: =J14-K14 -> 4112.2818 | M14: =M13+L14 -> 98054.903 | N14: =IF(M14<Supuestos!$B$4,"ALERTA","OK") -> OK | O14: =$K$2 -> 0.6
A15: =Datos!A12 -> Nov | B15: Proyectado | C15: =AVERAGE($C$8:$C$10)*(1+$E$2)^5 -> 916.13043 | D15: =AVERAGE($D$8:$D$10)*(1+$G$2) -> 98.666667 | E15: =C15*D15 -> 90391.535 | F15: =AVERAGE($F$8:$F$10)*(1+$I$2) -> 42 | G15: =C15*F15 -> 38477.478 | H15: =AVERAGE($H$8:$H$10) -> 46933.333 | I15: =E15-G15-H15 -> 4980.7242 | J15: =E15*O15+E14*(1-O14) -> 90033.549 | K15: =G15+H15 -> 85410.811 | L15: =J15-K15 -> 4622.7379 | M15: =M14+L15 -> 102677.64 | N15: =IF(M15<Supuestos!$B$4,"ALERTA","OK") -> OK | O15: =$K$2 -> 0.6
A16: =Datos!A13 -> Dic | B16: Proyectado | C16: =AVERAGE($C$8:$C$10)*(1+$E$2)^6 -> 925.29173 | D16: =AVERAGE($D$8:$D$10)*(1+$G$2) -> 98.666667 | E16: =C16*D16 -> 91295.451 | F16: =AVERAGE($F$8:$F$10)*(1+$I$2) -> 42 | G16: =C16*F16 -> 38862.253 | H16: =AVERAGE($H$8:$H$10) -> 46933.333 | I16: =E16-G16-H16 -> 5499.8648 | J16: =E16*O16+E15*(1-O15) -> 90933.885 | K16: =G16+H16 -> 85795.586 | L16: =J16-K16 -> 5138.2986 | M16: =M15+L16 -> 107815.94 | N16: =IF(M16<Supuestos!$B$4,"ALERTA","OK") -> OK | O16: =$K$2 -> 0.6
A17: Total | E17: =SUM(E5:E16) -> 1054166.6 | G17: =SUM(G5:G16) -> 445332.52 | H17: =SUM(H5:H16) -> 560500 | I17: =SUM(I5:I16) -> 48334.12 | J17: =SUM(J5:J16) -> 1053648.5 | K17: =SUM(K5:K16) -> 1005832.5 | L17: =SUM(L5:L16) -> 47815.939
A19: Cobros: % del mes en el mismo mes + resto del mes anterior (enero incluye las cuentas por cobrar iniciales). Pagos: costos variables y fijos en el mismo mes.

Sheet Flujo_Optimista
A1: Flujo de caja a 12 meses (USD)
A2: Escenario (1-3) | B2: 2 | C2: =INDEX(Supuestos!$B$8:$D$8,$B$2) -> Optimista | D2: Crec. vol. mensual | E2: =INDEX(Supuestos!$B$9:$D$9,$B$2) -> 0.025 | F2: Var. precio | G2: =INDEX(Supuestos!$B$10:$D$10,$B$2) -> 0.03 | H2: Var. costo var. | I2: =INDEX(Supuestos!$B$11:$D$11,$B$2) -> -0.02 | J2: % cobro mes | K2: =INDEX(Supuestos!$B$12:$D$12,$B$2) -> 0.7
A4: Mes | B4: Tipo | C4: Volumen | D4: Precio | E4: Ingresos | F4: Costo var. unit. | G4: Costo variable | H4: Gastos fijos | I4: Utilidad operativa | J4: Cobros | K4: Pagos | L4: Flujo neto | M4: Caja final | N4: Estado | O4: % cobro mes
A5: =Datos!A2 -> Ene | B5: Real | C5: =Datos!H2 -> 870 | D5: =Datos!I2 -> 98 | E5: =C5*D5 -> 85260 | F5: =Datos!J2 -> 41 | G5: =C5*F5 -> 35670 | H5: =Datos!K2+Datos!L2+Datos!M2 -> 45700 | I5: =E5-G5-H5 -> 3890 | J5: =E5*O5+Supuestos!$B$3 -> 87156 | K5: =G5+H5 -> 81370 | L5: =J5-K5 -> 5786 | M5: =Supuestos!$B$2+L5 -> 65786 | N5: =IF(M5<Supuestos!$B$4,"ALERTA","OK") -> OK | O5: =Supuestos!$B$5 -> 0.6
A6: =Datos!A3 -> Feb | B6: Real | C6: =Datos!H3 -> 905 | D6: =Datos!I3 -> 101 | E6: =C6*D6 -> 91405 | F6: =Datos!J3 -> 40 | G6: =C6*F6 -> 36200 | H6: =Datos!K3+Datos!L3+Datos!M3 -> 45300 | I6: =E6-G6-H6 -> 9905 | J6: =E6*O6+E5*(1-O5) -> 88947 | K6: =G6+H6 -> 81500 | L6: =J6-K6 -> 7447 | M6: =M5+L6 -> 73233 | N6: =IF(M6<Supuestos!$B$4,"ALERTA","OK") -> OK | O6: =Supuestos!$B$5 -> 0.6
A7: =Datos!A4 -> Mar | B7: Real | C7: =Datos!H4 -> 860 | D7: =Datos!I4 -> 99 | E7: =C7*D7 -> 85140 | F7: =Datos!J4 -> 42 | G7: =C7*F7 -> 36120 | H7: =Datos!K4+Datos!L4+Datos!M4 -> 47100 | I7: =E7-G7-H7 -> 1920 | J7: =E7*O7+E6*(1-O6) -> 87646 | K7: =G7+H7 -> 83220 | L7: =J7-K7 -> 4426 | M7: =M6+L7 -> 77659 | N7: =IF(M7<Supuestos!$B$4,"ALERTA","OK") -> OK | O7: =Supuestos!$B$5 -> 0.6
A8: =Datos!A5 -> Abr | B8: Real | C8: =Datos!H5 -> 880 | D8: =Datos!I5 -> 97 | E8: =C8*D8 -> 85360 | F8: =Datos!J5 -> 43 | G8: =C8*F8 -> 37840 | H8: =Datos!K5+Datos!L5+Datos!M5 -> 46400 | I8: =E8-G8-H8 -> 1120 | J8: =E8*O8+E7*(1-O7) -> 85272 | K8: =G8+H8 -> 84240 | L8: =J8-K8 -> 1032 | M8: =M7+L8 -> 78691 | N8: =IF(M8<Supuestos!$B$4,"ALERTA","OK") -> OK | O8: =Supuestos!$B$5 -> 0.6
A9: =Datos!A6 -> May | B9: Real | C9: =Datos!H6 -> 845 | D9: =Datos!I6 -> 100 | E9: =C9*D9 -> 84500 | F9: =Datos!J6 -> 41 | G9: =C9*F9 -> 34645 | H9: =Datos!K6+Datos!L6+Datos!M6 -> 46200 | I9: =E9-G9-H9 -> 3655 | J9: =E9*O9+E8*(1-O8) -> 84844 | K9: =G9+H9 -> 80845 | L9: =J9-K9 -> 3999 | M9: =M8+L9 -> 82690 | N9: =IF(M9<Supuestos!$B$4,"ALERTA","OK") -> OK | O9: =Supuestos!$B$5 -> 0.6
A10: =Datos!A7 -> Jun | B10: Real | C10: =Datos!H7 -> 890 | D10: =Datos!I7 -> 99 | E10: =C10*D10 -> 88110 | F10: =Datos!J7 -> 42 | G10: =C10*F10 -> 37380 | H10: =Datos!K7+Datos!L7+Datos!M7 -> 48200 | I10: =E10-G10-H10 -> 2530 | J10: =E10*O10+E9*(1-O9) -> 86666 | K10: =G10+H10 -> 85580 | L10: =J10-K10 -> 1086 | M10: =M9+L10 -> 83776 | N10: =IF(M10<Supuestos!$B$4,"ALERTA","OK") -> OK | O10: =Supuestos!$B$5 -> 0.6
A11: =Datos!A8 -> Jul | B11: Proyectado | C11: =AVERAGE($C$8:$C$10)*(1+$E$2)^1 -> 893.45833 | D11: =AVERAGE($D$8:$D$10)*(1+$G$2) -> 101.62667 | E11: =C11*D11 -> 90799.192 | F11: =AVERAGE($F$8:$F$10)*(1+$I$2) -> 41.16 | G11: =C11*F11 -> 36774.745 | H11: =AVERAGE($H$8:$H$10) -> 46933.333 | I11: =E11-G11-H11 -> 7091.1139 | J11: =E11*O11+E10*(1-O10) -> 98803.435 | K11: =G11+H11 -> 83708.078 | L11: =J11-K11 -> 15095.356 | M11: =M10+L11 -> 98871.356 | N11: =IF(M11<Supuestos!$B$4,"ALERTA","OK") -> OK | O11: =$K$2 -> 0.7
A12: =Datos!A9 -> Ago | B12: Proyectado | C12: =AVERAGE($C$8:$C$10)*(1+$E$2)^2 -> 915.79479 | D12: =AVERAGE($D$8:$D$10)*(1+$G$2) -> 101.62667 | E12: =C12*D12 -> 93069.172 | F12: =AVERAGE($F$8:$F$10)*(1+$I$2) -> 41.16 | G12: =C12*F12 -> 37694.114 | H12: =AVERAGE($H$8:$H$10) -> 46933.333 | I12: =E12-G12-H12 -> 8441.7251 | J12: =E12*O12+E11*(1-O11) -> 92388.178 | K12: =G12+H12 -> 84627.447 | L12: =J12-K12 -> 7760.7311 | M12: =M11+L12 -> 106632.09 | N12: =IF(M12<Supuestos!$B$4,"ALERTA","OK") -> OK | O12: =$K$2 -> 0.7
A13: =Datos!A10 -> Sep | B13: Proyectado | C13: =AVERAGE($C$8:$C$10)*(1+$E$2)^3 -> 938.68966 | D13: =AVERAGE($D$8:$D$10)*(1+$G$2) -> 101.62667 | E13: =C13*D13 -> 95395.901 | F13: =AVERAGE($F$8:$F$10)*(1+$I$2) -> 41.16 | G13: =C13*F13 -> 38636.466 | H13: =AVERAGE($H$8:$H$10) -> 46933.333 | I13: =E13-G13-H13 -> 9826.1015 | J13: =E13*O13+E12*(1-O12) -> 94697.883 | K13: =G13+H13 -> 85569.8 | L13: =J13-K13 -> 9128.0827 | M13: =M12+L13 -> 115760.17 | N13: =IF(M13<Supuestos!$B$4,"ALERTA","OK") -> OK | O13: =$K$2 -> 0.7
A14: =Datos!A11 -> Oct | B14: Proyectado | C14: =AVERAGE($C$8:$C$10)*(1+$E$2)^4 -> 962.1569 | D14: =AVERAGE($D$8:$D$10)*(1+$G$2) -> 101.62667 | E14: =C14*D14 -> 97780.799 | F14: =AVERAGE($F$8:$F$10)*(1+$I$2) -> 41.16 | G14: =C14*F14 -> 39602.378 | H14: =AVERAGE($H$8:$H$10) -> 46933.333 | I14: =E14-G14-H14 -> 11245.087 | J14: =E14*O14+E13*(1-O13) -> 97065.33 | K14: =G14+H14 -> 86535.711 | L14: =J14-K14 -> 10529.618 | M14: =M13+L14 -> 126289.79 | N14: =IF(M14<Supuestos!$B$4,"ALERTA","OK") -> OK | O14: =$K$2 -> 0.7
A15: =Datos!A12 -> Nov | B15: Proyectado | C15: =AVERAGE($C$8:$C$10)*(1+$E$2)^5 -> 986.21083 | D15: =AVERAGE($D$8:$D$10)*(1+$G$2) -> 101.62667 | E15: =C15*D15 -> 100225.32 | F15: =AVERAGE($F$8:$F$10)*(1+$I$2) -> 41.16 | G15: =C15*F15 -> 40592.438 | H15: =AVERAGE($H$8:$H$10) -> 46933.333 | I15: =E15-G15-H15 -> 12699.548 | J15: =E15*O15+E14*(1-O14) -> 99491.963 | K15: =G15+H15 -> 87525.771 | L15: =J15-K15 -> 11966.192 | M15: =M14+L15 -> 138255.98 | N15: =IF(M15<Supuestos!$B$4,"ALERTA","OK") -> OK | O15: =$K$2 -> 0.7
A16: =Datos!A13 -> Dic | B16: Proyectado | C16: =AVERAGE($C$8:$C$10)*(1+$E$2)^6 -> 1010.8661 | D16: =AVERAGE($D$8:$D$10)*(1+$G$2) -> 101.62667 | E16: =C16*D16 -> 102730.95 | F16: =AVERAGE($F$8:$F$10)*(1+$I$2) -> 41.16 | G16: =C16*F16 -> 41607.249 | H16: =AVERAGE($H$8:$H$10) -> 46933.333 | I16: =E16-G16-H16 -> 14190.37 | J16: =E16*O16+E15*(1-O15) -> 101979.26 | K16: =G16+H16 -> 88540.582 | L16: =J16-K16 -> 13438.68 | M16: =M15+L16 -> 151694.66 | N16: =IF(M16<Supuestos!$B$4,"ALERTA","OK") -> OK | O16: =$K$2 -> 0.7
A17: Total | E17: =SUM(E5:E16) -> 1099776.3 | G17: =SUM(G5:G16) -> 452762.39 | H17: =SUM(H5:H16) -> 560500 | I17: =SUM(I5:I16) -> 86513.946 | J17: =SUM(J5:J16) -> 1104957 | K17: =SUM(K5:K16) -> 1013262.4 | L17: =SUM(L5:L16) -> 91694.66
A19: Cobros: % del mes en el mismo mes + resto del mes anterior (enero incluye las cuentas por cobrar iniciales). Pagos: costos variables y fijos en el mismo mes.

Sheet Flujo_Pesimista
A1: Flujo de caja a 12 meses (USD)
A2: Escenario (1-3) | B2: 3 | C2: =INDEX(Supuestos!$B$8:$D$8,$B$2) -> Pesimista | D2: Crec. vol. mensual | E2: =INDEX(Supuestos!$B$9:$D$9,$B$2) -> -0.01 | F2: Var. precio | G2: =INDEX(Supuestos!$B$10:$D$10,$B$2) -> -0.02 | H2: Var. costo var. | I2: =INDEX(Supuestos!$B$11:$D$11,$B$2) -> 0.04 | J2: % cobro mes | K2: =INDEX(Supuestos!$B$12:$D$12,$B$2) -> 0.45
A4: Mes | B4: Tipo | C4: Volumen | D4: Precio | E4: Ingresos | F4: Costo var. unit. | G4: Costo variable | H4: Gastos fijos | I4: Utilidad operativa | J4: Cobros | K4: Pagos | L4: Flujo neto | M4: Caja final | N4: Estado | O4: % cobro mes
A5: =Datos!A2 -> Ene | B5: Real | C5: =Datos!H2 -> 870 | D5: =Datos!I2 -> 98 | E5: =C5*D5 -> 85260 | F5: =Datos!J2 -> 41 | G5: =C5*F5 -> 35670 | H5: =Datos!K2+Datos!L2+Datos!M2 -> 45700 | I5: =E5-G5-H5 -> 3890 | J5: =E5*O5+Supuestos!$B$3 -> 87156 | K5: =G5+H5 -> 81370 | L5: =J5-K5 -> 5786 | M5: =Supuestos!$B$2+L5 -> 65786 | N5: =IF(M5<Supuestos!$B$4,"ALERTA","OK") -> OK | O5: =Supuestos!$B$5 -> 0.6
A6: =Datos!A3 -> Feb | B6: Real | C6: =Datos!H3 -> 905 | D6: =Datos!I3 -> 101 | E6: =C6*D6 -> 91405 | F6: =Datos!J3 -> 40 | G6: =C6*F6 -> 36200 | H6: =Datos!K3+Datos!L3+Datos!M3 -> 45300 | I6: =E6-G6-H6 -> 9905 | J6: =E6*O6+E5*(1-O5) -> 88947 | K6: =G6+H6 -> 81500 | L6: =J6-K6 -> 7447 | M6: =M5+L6 -> 73233 | N6: =IF(M6<Supuestos!$B$4,"ALERTA","OK") -> OK | O6: =Supuestos!$B$5 -> 0.6
A7: =Datos!A4 -> Mar | B7: Real | C7: =Datos!H4 -> 860 | D7: =Datos!I4 -> 99 | E7: =C7*D7 -> 85140 | F7: =Datos!J4 -> 42 | G7: =C7*F7 -> 36120 | H7: =Datos!K4+Datos!L4+Datos!M4 -> 47100 | I7: =E7-G7-H7 -> 1920 | J7: =E7*O7+E6*(1-O6) -> 87646 | K7: =G7+H7 -> 83220 | L7: =J7-K7 -> 4426 | M7: =M6+L7 -> 77659 | N7: =IF(M7<Supuestos!$B$4,"ALERTA","OK") -> OK | O7: =Supuestos!$B$5 -> 0.6
A8: =Datos!A5 -> Abr | B8: Real | C8: =Datos!H5 -> 880 | D8: =Datos!I5 -> 97 | E8: =C8*D8 -> 85360 | F8: =Datos!J5 -> 43 | G8: =C8*F8 -> 37840 | H8: =Datos!K5+Datos!L5+Datos!M5 -> 46400 | I8: =E8-G8-H8 -> 1120 | J8: =E8*O8+E7*(1-O7) -> 85272 | K8: =G8+H8 -> 84240 | L8: =J8-K8 -> 1032 | M8: =M7+L8 -> 78691 | N8: =IF(M8<Supuestos!$B$4,"ALERTA","OK") -> OK | O8: =Supuestos!$B$5 -> 0.6
A9: =Datos!A6 -> May | B9: Real | C9: =Datos!H6 -> 845 | D9: =Datos!I6 -> 100 | E9: =C9*D9 -> 84500 | F9: =Datos!J6 -> 41 | G9: =C9*F9 -> 34645 | H9: =Datos!K6+Datos!L6+Datos!M6 -> 46200 | I9: =E9-G9-H9 -> 3655 | J9: =E9*O9+E8*(1-O8) -> 84844 | K9: =G9+H9 -> 80845 | L9: =J9-K9 -> 3999 | M9: =M8+L9 -> 82690 | N9: =IF(M9<Supuestos!$B$4,"ALERTA","OK") -> OK | O9: =Supuestos!$B$5 -> 0.6
A10: =Datos!A7 -> Jun | B10: Real | C10: =Datos!H7 -> 890 | D10: =Datos!I7 -> 99 | E10: =C10*D10 -> 88110 | F10: =Datos!J7 -> 42 | G10: =C10*F10 -> 37380 | H10: =Datos!K7+Datos!L7+Datos!M7 -> 48200 | I10: =E10-G10-H10 -> 2530 | J10: =E10*O10+E9*(1-O9) -> 86666 | K10: =G10+H10 -> 85580 | L10: =J10-K10 -> 1086 | M10: =M9+L10 -> 83776 | N10: =IF(M10<Supuestos!$B$4,"ALERTA","OK") -> OK | O10: =Supuestos!$B$5 -> 0.6
A11: =Datos!A8 -> Jul | B11: Proyectado | C11: =AVERAGE($C$8:$C$10)*(1+$E$2)^1 -> 862.95 | D11: =AVERAGE($D$8:$D$10)*(1+$G$2) -> 96.693333 | E11: =C11*D11 -> 83441.512 | F11: =AVERAGE($F$8:$F$10)*(1+$I$2) -> 43.68 | G11: =C11*F11 -> 37693.656 | H11: =AVERAGE($H$8:$H$10) -> 46933.333 | I11: =E11-G11-H11 -> -1185.4773 | J11: =E11*O11+E10*(1-O10) -> 72792.68 | K11: =G11+H11 -> 84626.989 | L11: =J11-K11 -> -11834.309 | M11: =M10+L11 -> 71941.691 | N11: =IF(M11<Supuestos!$B$4,"ALERTA","OK") -> OK | O11: =$K$2 -> 0.45
A12: =Datos!A9 -> Ago | B12: Proyectado | C12: =AVERAGE($C$8:$C$10)*(1+$E$2)^2 -> 854.3205 | D12: =AVERAGE($D$8:$D$10)*(1+$G$2) -> 96.693333 | E12: =C12*D12 -> 82607.097 | F12: =AVERAGE($F$8:$F$10)*(1+$I$2) -> 43.68 | G12: =C12*F12 -> 37316.719 | H12: =AVERAGE($H$8:$H$10) -> 46933.333 | I12: =E12-G12-H12 -> -1642.9559 | J12: =E12*O12+E11*(1-O11) -> 83066.025 | K12: =G12+H12 -> 84250.053 | L12: =J12-K12 -> -1184.0276 | M12: =M11+L12 -> 70757.663 | N12: =IF(M12<Supuestos!$B$4,"ALERTA","OK") -> OK | O12: =$K$2 -> 0.45
A13: =Datos!A10 -> Sep | B13: Proyectado | C13: =AVERAGE($C$8:$C$10)*(1+$E$2)^3 -> 845.77729 | D13: =AVERAGE($D$8:$D$10)*(1+$G$2) -> 96.693333 | E13: =C13*D13 -> 81781.026 | F13: =AVERAGE($F$8:$F$10)*(1+$I$2) -> 43.68 | G13: =C13*F13 -> 36943.552 | H13: =AVERAGE($H$8:$H$10) -> 46933.333 | I13: =E13-G13-H13 -> -2095.8597 | J13: =E13*O13+E12*(1-O12) -> 82235.365 | K13: =G13+H13 -> 83876.886 | L13: =J13-K13 -> -1641.5206 | M13: =M12+L13 -> 69116.143 | N13: =IF(M13<Supuestos!$B$4,"ALERTA","OK") -> OK | O13: =$K$2 -> 0.45
A14: =Datos!A11 -> Oct | B14: Proyectado | C14: =AVERAGE($C$8:$C$10)*(1+$E$2)^4 -> 837.31952 | D14: =AVERAGE($D$8:$D$10)*(1+$G$2) -> 96.693333 | E14: =C14*D14 -> 80963.216 | F14: =AVERAGE($F$8:$F$10)*(1+$I$2) -> 43.68 | G14: =C14*F14 -> 36574.117 | H14: =AVERAGE($H$8:$H$10) -> 46933.333 | I14: =E14-G14-H14 -> -2544.2344 | J14: =E14*O14+E13*(1-O13) -> 81413.011 | K14: =G14+H14 -> 83507.45 | L14: =J14-K14 -> -2094.4388 | M14: =M13+L14 -> 67021.704 | N14: =IF(M14<Supuestos!$B$4,"ALERTA","OK") -> OK | O14: =$K$2 -> 0.45
A15: =Datos!A12 -> Nov | B15: Proyectado | C15: =AVERAGE($C$8:$C$10)*(1+$E$2)^5 -> 828.94633 | D15: =AVERAGE($D$8:$D$10)*(1+$G$2) -> 96.693333 | E15: =C15*D15 -> 80153.583 | F15: =AVERAGE($F$8:$F$10)*(1+$I$2) -> 43.68 | G15: =C15*F15 -> 36208.376 | H15: =AVERAGE($H$8:$H$10) -> 46933.333 | I15: =E15-G15-H15 -> -2988.1254 | J15: =E15*O15+E14*(1-O14) -> 80598.881 | K15: =G15+H15 -> 83141.709 | L15: =J15-K15 -> -2542.8277 | M15: =M14+L15 -> 64478.876 | N15: =IF(M15<Supuestos!$B$4,"ALERTA","OK") -> ALERTA | O15: =$K$2 -> 0.45
A16: =Datos!A13 -> Dic | B16: Proyectado | C16: =AVERAGE($C$8:$C$10)*(1+$E$2)^6 -> 820.65686 | D16: =AVERAGE($D$8:$D$10)*(1+$G$2) -> 96.693333 | E16: =C16*D16 -> 79352.048 | F16: =AVERAGE($F$8:$F$10)*(1+$I$2) -> 43.68 | G16: =C16*F16 -> 35846.292 | H16: =AVERAGE($H$8:$H$10) -> 46933.333 | I16: =E16-G16-H16 -> -3427.5775 | J16: =E16*O16+E15*(1-O15) -> 79792.892 | K16: =G16+H16 -> 82779.625 | L16: =J16-K16 -> -2986.7328 | M16: =M15+L16 -> 61492.144 | N16: =IF(M16<Supuestos!$B$4,"ALERTA","OK") -> ALERTA | O16: =$K$2 -> 0.45
A17: Total | E17: =SUM(E5:E16) -> 1008073.5 | G17: =SUM(G5:G16) -> 438437.71 | H17: =SUM(H5:H16) -> 560500 | I17: =SUM(I5:I16) -> 9135.7698 | J17: =SUM(J5:J16) -> 1000429.9 | K17: =SUM(K5:K16) -> 998937.71 | L17: =SUM(L5:L16) -> 1492.1436
A19: Cobros: % del mes en el mismo mes + resto del mes anterior (enero incluye las cuentas por cobrar iniciales). Pagos: costos variables y fijos en el mismo mes.
